MANIFEST.in
README.txt
setup.cfg
setup.py
Products/__init__.py
Products.HitList.egg-info/PKG-INFO
Products.HitList.egg-info/SOURCES.txt
Products.HitList.egg-info/dependency_links.txt
Products.HitList.egg-info/entry_points.txt
Products.HitList.egg-info/namespace_packages.txt
Products.HitList.egg-info/not-zip-safe
Products.HitList.egg-info/requires.txt
Products.HitList.egg-info/top_level.txt
Products/HitList/__init__.py
Products/HitList/config.py
Products/HitList/configure.zcml
Products/HitList/interfaces.py
Products/HitList/setuphandlers.py
Products/HitList/utils.py
Products/HitList/browser/__init__.py
Products/HitList/browser/configure.zcml
Products/HitList/browser/hitlist.py
Products/HitList/browser/hitlist_icon.gif
Products/HitList/browser/portlet.py
Products/HitList/browser/views.py
Products/HitList/browser/templates/hitlist.pt
Products/HitList/browser/templates/portlet.pt
Products/HitList/browser/templates/viewlet.pt
Products/HitList/content/__init__.py
Products/HitList/content/hitlist.py
Products/HitList/i18n/HitList-de-plone.mo
Products/HitList/i18n/HitList-de-plone.po
Products/HitList/i18n/HitList-de.mo
Products/HitList/i18n/HitList-de.po
Products/HitList/i18n/HitList-fr-plone.mo
Products/HitList/i18n/HitList-fr-plone.po
Products/HitList/i18n/HitList-fr.mo
Products/HitList/i18n/HitList-fr.po
Products/HitList/profiles/default/Products.HitList_various.txt
Products/HitList/profiles/default/import_steps.xml
Products/HitList/profiles/default/metadata.xml
Products/HitList/profiles/default/portlets.xml
Products/HitList/profiles/default/rolemap.xml
Products/HitList/profiles/default/types.xml
Products/HitList/profiles/default/types/HitList.xml
docs/HISTORY.txt