Metadata-Version: 1.0
Name: Products.HitList
Version: 2.0b4
Summary: Provides a personal hit-list which may be displayed in a portlet or a view
Home-page: https://svn.plone.org/svn/collective/Products.HitList
Author: Raptus AG
Author-email: dev@raptus.com
License: GPL
Platform: UNKNOWN
Classifier: Programming Language :: Python
Classifier: Topic :: Software Development :: Libraries :: Python Modules
